README.rst
setup.cfg
setup.py
beets_copyartifacts.egg-info/PKG-INFO
beets_copyartifacts.egg-info/SOURCES.txt
beets_copyartifacts.egg-info/dependency_links.txt
beets_copyartifacts.egg-info/namespace_packages.txt
beets_copyartifacts.egg-info/requires.txt
beets_copyartifacts.egg-info/top_level.txt
beetsplug/__init__.py
beetsplug/copyartifacts.py