Metadata-Version: 1.1
Name: beets-copyartifacts
Version: 0.1.2
Summary: beets plugin to copy non-music files to import path
Home-page: https://github.com/sbarakat/beets-copyartifacts
Author: Sami Barakat
Author-email: sami@sbarakat.co.uk
License: MIT
Download-URL: https://github.com/sbarakat/beets-copyartifacts.git
Platform: UNKNOWN
